main/__init__.py
main/customerrors.py
main/pgame.py
main/pgame_test.py
tests/__init__.py
tests/customerrors.py
tests/pgame.py
tests/pgame_test.py
splatboy_test-0.0.1.dist-info/METADATA
splatboy_test-0.0.1.dist-info/WHEEL
splatboy_test-0.0.1.dist-info/top_level.txt
splatboy_test-0.0.1.dist-info/RECORD
