Metadata-Version: 2.1
Name: splatboy-test
Version: 0.0.1
Summary: A pypi test.
Home-page: http://packages.python.org/splatboy_test
Author: Splatboy Dev
Author-email: splatboy20081@gmail.com
License: GPL v3.0
Keywords: example documentation tutorial
Platform: UNKNOWN
Classifier: Development Status :: 3 - Alpha
Classifier: Topic :: Utilities
Classifier: License :: OSI Approved :: BSD License
